FireHR/__init__.py
FireHR/_nbdev.py
FireHR/cli.py
FireHR/data.py
FireHR/models.py
FireHR/predict.py
FireHR-0.1.6.dist-info/LICENSE
FireHR-0.1.6.dist-info/METADATA
FireHR-0.1.6.dist-info/WHEEL
FireHR-0.1.6.dist-info/entry_points.txt
FireHR-0.1.6.dist-info/top_level.txt
FireHR-0.1.6.dist-info/RECORD
