Metadata-Version: 2.1
Name: FireHR
Version: 0.1.6
Summary: High-resolution burned areas using Sentinel-2 data
Home-page: https://github.com/mnpinto/FireHR/tree/master/
Author: Miguel Pinto
Author-email: mnpinto@fc.ul.pt
License: Apache Software License 2.0
Keywords: Burned Areas,Wildfires,Sentinel-2,VIIRS,Deep Learning
Platform: UNKNOWN
Classifier: Development Status :: 3 - Alpha
Classifier: Intended Audience :: Developers
Classifier: License :: OSI Approved :: Apache Software License
Classifier: Natural Language :: English
Classifier: Programming Language :: Python :: 3.6
Classifier: Programming Language :: Python :: 3.7
Classifier: Programming Language :: Python :: 3.8
Requires-Python: >=3.6
Requires-Dist: earthengine-api
Requires-Dist: banet (==0.6.5)
Requires-Dist: fastai (<2.2.7,>=2.1.4)
Requires-Dist: fastprogress
